_yenc.so
yenc.py
yenc-0.4.0.dist-info/DESCRIPTION.rst
yenc-0.4.0.dist-info/METADATA
yenc-0.4.0.dist-info/RECORD
yenc-0.4.0.dist-info/WHEEL
yenc-0.4.0.dist-info/metadata.json
yenc-0.4.0.dist-info/top_level.txt
