Metadata-Version: 1.1
Name: yenc
Version: 0.4.0
Summary: yEnc Module for Python
Home-page: https://bitbucket.org/dual75/yenc
Author: Alessandro Duca
Author-email: alessandro.duca@gmail.com
License: LGPL
Platform: UNKNOWN
Classifier: Programming Language :: Python
Classifier: Programming Language :: Python :: 2.5
Classifier: Programming Language :: Python :: 2.6
Classifier: Programming Language :: Python :: 2.7
Classifier: Programming Language :: C
Classifier: License :: OSI Approved :: GNU Library or Lesser General Public License (LGPL)
Classifier: Operating System :: Unix
Classifier: Development Status :: 4 - Beta
Classifier: Environment :: Other Environment
Classifier: Intended Audience :: Developers
Classifier: Topic :: Software Development :: Libraries :: Python Modules
Classifier: Topic :: Communications :: Usenet News
